ipv8_taskmanager/__init__.py
ipv8_taskmanager-1.0.0.dist-info/METADATA
ipv8_taskmanager-1.0.0.dist-info/WHEEL
ipv8_taskmanager-1.0.0.dist-info/top_level.txt
ipv8_taskmanager-1.0.0.dist-info/RECORD
